CHANGES.txt
README.txt
TODO.txt
bootstrap.py
buildout.cfg
setup.cfg
setup.py
tha/__init__.py
tha.taglist.egg-info/PKG-INFO
tha.taglist.egg-info/SOURCES.txt
tha.taglist.egg-info/dependency_links.txt
tha.taglist.egg-info/entry_points.txt
tha.taglist.egg-info/namespace_packages.txt
tha.taglist.egg-info/not-zip-safe
tha.taglist.egg-info/requires.txt
tha.taglist.egg-info/top_level.txt
tha/taglist/__init__.py
tha/taglist/defaults.py
tha/taglist/exporter.py
tha/taglist/templates/index.html