Metadata-Version: 1.0
Name: tha.taglist
Version: 1.5
Summary: Create find-links list of tags
Home-page: http://thehealthagency.com
Author: The Health Agency
Author-email: techniek@thehealthagency.com
License: ZPL
Platform: UNKNOWN
Classifier: Programming Language :: Python
Classifier: Topic :: Software Development :: Libraries :: Python Modules
